[{"family":"MaterialIcons","fonts":[{"asset":"fonts/MaterialIcons-Regular.otf"}]},{"family":"Noto","fonts":[{"asset":"fonts/noto.otf"}]},{"family":"lr","fonts":[{"asset":"fonts/lr.ttf"}]},{"family":"um","fonts":[{"asset":"fonts/um.ttf"}]},{"family":"Manrope","fonts":[{"asset":"fonts/Manrope-Regular.ttf"},{"asset":"fonts/Manrope-Bold.ttf"},{"asset":"fonts/Manrope-ExtraBold.ttf"},{"asset":"fonts/Manrope-Light.ttf"},{"asset":"fonts/Manrope-Medium.ttf"},{"asset":"fonts/Manrope-SemiBold.ttf"}]},{"family":"packages/cupertino_icons/CupertinoIcons","fonts":[{"asset":"packages/cupertino_icons/assets/CupertinoIcons.ttf"}]}]